IDE/CCodeEditor.py
IDE/CCodeEditor_FC.py
IDE/CCodeEditor_PRG.py
IDE/CDeclar_Axis.py
IDE/CDeclar_Enum.py
IDE/CDeclar_Menber.py
IDE/CDeclar_Menber_FB.py
IDE/CDeclar_Menber_Hardware.py
IDE/CDeclar_Task.py
IDE/CHelpBuilder.py
IDE/CLogText.py
IDE/CNotebook.py
IDE/CProjectTree.py
IDE/Parse.py
IDE/StaticLibary.py
IDE/__init__.py
IDE/framework.py
lib/CDictExpressParse.py
lib/CommonDialog.py
lib/DataGroup.py
lib/ExpressToken.py
lib/File.py
lib/File_Serialize.py
lib/GridEditor.py
lib/JsonClass.py
lib/PTrend.py
lib/ScadaAPI.py
lib/ScadaCommon.py
lib/StringOperation.py
lib/ValidatorEditor.py
lib/__init__.py
lib/loadjson.py
lib/markdown2html.py
lib/prettytable.py
test/__init__.py
test/gdb_test.py
test/master_webhmi.py
PLC_IDE-0.0.2.dist-info/LICENSE
PLC_IDE-0.0.2.dist-info/METADATA
PLC_IDE-0.0.2.dist-info/WHEEL
PLC_IDE-0.0.2.dist-info/top_level.txt
PLC_IDE-0.0.2.dist-info/RECORD
