Metadata-Version: 2.1
Name: PLC-IDE
Version: 0.0.2
Summary: PLC PRG EDITOR tool
Home-page: UNKNOWN
Author: ren1987yi
Author-email: ren1987yi@163.com
License: MIT Licence
Keywords: pip,pathtool,timetool,magetool,mage
Platform: any
